ATmulti_file_handler/__init__.py
ATmulti_file_handler/core.py
atmulti_file_handler-2.0.2.dist-info/licenses/LICENSE
atmulti_file_handler-2.0.2.dist-info/METADATA
atmulti_file_handler-2.0.2.dist-info/WHEEL
atmulti_file_handler-2.0.2.dist-info/top_level.txt
atmulti_file_handler-2.0.2.dist-info/RECORD
