Metadata-Version: 2.4
Name: ATmulti_file_handler
Version: 2.0.2
Summary: A unified file handling abstraction layer for multiple file formats.
Author-email: Avi Twil <avitwil@gmail.com>
License: MIT
Project-URL: Homepage, https://github.com/avitwil/ATmulti_file_handler
Project-URL: Source, https://github.com/avitwil/ATmulti_file_handler
Project-URL: Bug Tracker, https://github.com/avitwil/ATmulti_file_handler/issues
Keywords: file,txt,json,csv,yaml,xml,dill,binary,database,VarDB
Classifier: Development Status :: 5 - Production/Stable
Classifier: Programming Language :: Python :: 3
Classifier: License :: OSI Approved :: MIT License
Classifier: Operating System :: OS Independent
Classifier: Topic :: Utilities
Requires-Python: >=3.10
License-File: LICENSE
Requires-Dist: dill>=0.3.6
Requires-Dist: PyYAML>=6.0
Requires-Dist: avi_tools>=1.0.0
Dynamic: license-file
